guilib/__init__.py
guilib/chartslider/__init__.py
guilib/chartslider/rangeslider.py
guilib/chartslider/rangeslider.qml
guilib/chartslider/xchartslider.py
guilib/chartslider/ychartslider.py
guilib/chartwidget/__init__.py
guilib/chartwidget/chart.py
guilib/chartwidget/charthover.py
guilib/chartwidget/charthoverui.ui
guilib/chartwidget/chartview.py
guilib/chartwidget/chartwidget.py
guilib/chartwidget/datetimeaxis.py
guilib/chartwidget/model.py
guilib/chartwidget/modelgui.py
guilib/chartwidget/viewmodel.py
guilib/dates/__init__.py
guilib/dates/converters.py
guilib/dates/generators.py
guilib/doubler/__init__.py
guilib/doubler/doubler.py
guilib/multitabs/__init__.py
guilib/multitabs/widget.py
guilib/py.typed
guilib/qwtplot/__init__.py
guilib/qwtplot/plot.py
guilib/qwtplot/scaledraw.py
guilib/searchsheet/__init__.py
guilib/searchsheet/model.py
guilib/searchsheet/widget.py
zeed_guilib-0.0.13.dist-info/METADATA
zeed_guilib-0.0.13.dist-info/WHEEL
zeed_guilib-0.0.13.dist-info/entry_points.txt
zeed_guilib-0.0.13.dist-info/licenses/LICENSE
zeed_guilib-0.0.13.dist-info/RECORD
