Metadata-Version: 2.1
Name: zeed-guilib
Version: 0.0.13
License:                     GNU AFFERO GENERAL PUBLIC LICENSE
Classifier: Programming Language :: Python :: 3 :: Only
Classifier: Programming Language :: Python :: 3.12
Classifier: Programming Language :: Python :: 3.13
Project-URL: Homepage, https://github.com/ZeeD/guilib
Project-URL: Repository, https://github.com/ZeeD/guilib.git
Requires-Python: <3.14,>=3.12
Requires-Dist: pyside6-addons>=6.10
Requires-Dist: pyside6-essentials>=6.10
Requires-Dist: pythonqwt>=0.14.4
